plotly_utils/__init__.py
plotly_utils-0.0.3.dist-info/METADATA
plotly_utils-0.0.3.dist-info/WHEEL
plotly_utils-0.0.3.dist-info/top_level.txt
plotly_utils-0.0.3.dist-info/RECORD
