Metadata-Version: 2.1
Name: plotly-utils
Version: 0.0.3
Summary: High level API for plotting via Plotly in Jupyter Notebook
Home-page: https://github.com/gkovacs/plotly-utils
Author: Geza Kovacs
Author-email: noreply@gkovacs.com
License: UNKNOWN
Platform: UNKNOWN
Classifier: Programming Language :: Python :: 3
Classifier: License :: OSI Approved :: MIT License
Classifier: Operating System :: OS Independent
